src/cli.py
src/detacsv.py
csv_deta-0.5.1a34.dist-info/LICENSE
csv_deta-0.5.1a34.dist-info/METADATA
csv_deta-0.5.1a34.dist-info/WHEEL
csv_deta-0.5.1a34.dist-info/entry_points.txt
csv_deta-0.5.1a34.dist-info/top_level.txt
csv_deta-0.5.1a34.dist-info/RECORD
