Metadata-Version: 2.1
Name: csv-deta
Version: 0.5.1a34
Summary: Lightweight tool to upload and download CSV data files into\from Deta Base
Author: JL Connor
License: Apache Software License 2.0
Keywords: csv,db,database,deta,cli,detabase,upload,download,backup
Classifier: Development Status :: 3 - Alpha
Classifier: Programming Language :: Python :: 3
Classifier: License :: OSI Approved :: Apache Software License
Classifier: License :: Freeware
Classifier: Intended Audience :: Developers
Classifier: Topic :: Software Development :: Libraries :: Python Modules
Classifier: Topic :: Utilities
Requires-Python: >=3
License-File: LICENSE
Requires-Dist: deta
Requires-Dist: fire
